{
    "ɔː": {
        "IPA": "ɔː",
        "KK": "ɔ",
        "CMU": "AO"
    },
    "ɒ": {
        "IPA": "ɒ",
        "KK": "ɔ",
        "CMU": "OH"
    },
    "ɑː": {
        "IPA": "ɑː",
        "KK": "ɑ",
        "CMU": "AA"
    },
    "i": {
        "IPA": "i",
        "KK": "i",
        "CMU": "IX"
    },
    "iː": {
        "IPA": "iː",
        "KK": "i",
        "CMU": "IY"
    },
    "uː": {
        "IPA": "uː",
        "KK": "u",
        "CMU": "UW"
    },
    "u": {
        "IPA": "u",
        "KK": "u",
        "CMU": "UX"
    },
    "e": {
        "IPA": "e",
        "KK": "ɛ",
        "CMU": "EH"
    },
    "ɪ": {
        "IPA": "ɪ",
        "KK": "ɪ",
        "CMU": "IH"
    },
    "ʊ": {
        "IPA": "ʊ",
        "KK": "ʊ",
        "CMU": "UH"
    },
    "ʌ": {
        "IPA": "ʌ",
        "KK": "ʌ",
        "CMU": "AH"
    },
    "ə": {
        "IPA": "ə",
        "KK": "ə",
        "CMU": "AX"
    },
    "ər": {
        "IPA": "ər",
        "KK": "ɚ",
        "CMU": "AXR"
    },
    "æ": {
        "IPA": "æ",
        "KK": "æ",
        "CMU": "AE"
    },
    "eɪ": {
        "IPA": "eɪ",
        "KK": "e",
        "CMU": "EY"
    },
    "aɪ": {
        "IPA": "aɪ",
        "KK": "aɪ",
        "CMU": "AY"
    },
    "əʊ": {
        "IPA": "əʊ",
        "KK": "oʊ",
        "CMU": "OW"
    },
    "aʊ": {
        "IPA": "aʊ",
        "KK": "aʊ",
        "CMU": "AW"
    },
    "ɔɪ": {
        "IPA": "ɔɪ",
        "KK": "ɔɪ",
        "CMU": "OY"
    },
    "p": {
        "IPA": "p",
        "KK": "p",
        "CMU": "P"
    },
    "b": {
        "IPA": "b",
        "KK": "b",
        "CMU": "B"
    },
    "t": {
        "IPA": "t",
        "KK": "t",
        "CMU": "T"
    },
    "d": {
        "IPA": "d",
        "KK": "d",
        "CMU": "D"
    },
    "k": {
        "IPA": "k",
        "KK": "k",
        "CMU": "K"
    },
    "ɡ": {
        "IPA": "ɡ",
        "KK": "ɡ",
        "CMU": "G"
    },
    "tʃ": {
        "IPA": "tʃ",
        "KK": "tʃ",
        "CMU": "CH"
    },
    "dʒ": {
        "IPA": "dʒ",
        "KK": "dʒ",
        "CMU": "JH"
    },
    "f": {
        "IPA": "f",
        "KK": "f",
        "CMU": "F"
    },
    "v": {
        "IPA": "v",
        "KK": "v",
        "CMU": "V"
    },
    "θ": {
        "IPA": "θ",
        "KK": "θ",
        "CMU": "TH"
    },
    "ð": {
        "IPA": "ð",
        "KK": "ð",
        "CMU": "DH"
    },
    "s": {
        "IPA": "s",
        "KK": "s",
        "CMU": "S"
    },
    "z": {
        "IPA": "z",
        "KK": "z",
        "CMU": "Z"
    },
    "ʃ": {
        "IPA": "ʃ",
        "KK": "ʃ",
        "CMU": "SH"
    },
    "ʒ": {
        "IPA": "ʒ",
        "KK": "ʒ",
        "CMU": "ZH"
    },
    "h": {
        "IPA": "h",
        "KK": "h",
        "CMU": "HH"
    },
    "m": {
        "IPA": "m",
        "KK": "m",
        "CMU": "M"
    },
    "n": {
        "IPA": "n",
        "KK": "n",
        "CMU": "N"
    },
    "ŋ": {
        "IPA": "ŋ",
        "KK": "ŋ",
        "CMU": "NG"
    },
    "l": {
        "IPA": "l",
        "KK": "l",
        "CMU": "L"
    },
    "r": {
        "IPA": "r",
        "KK": "r",
        "CMU": "R"
    },
    "ɜː": {
        "IPA": "ɜː",
        "KK": "ɝ",
        "CMU": "ER"
    },
    "w": {
        "IPA": "w",
        "KK": "w",
        "CMU": "W"
    },
    "j": {
        "IPA": "j",
        "KK": "j",
        "CMU": "Y"
    }
}